izlearn/__init__.py
izlearn/vision/__init__.py
izlearn/vision/image_explorer.py
izlearn-1.0.1.dist-info/METADATA
izlearn-1.0.1.dist-info/WHEEL
izlearn-1.0.1.dist-info/top_level.txt
izlearn-1.0.1.dist-info/RECORD
