Metadata-Version: 2.1
Name: izlearn
Version: 1.0.1
Summary: Python package for simplifying machine learning projects
Author: izzalDev
License: MIT
Requires-Dist: numpy
Requires-Dist: scikit-image
Requires-Dist: opencv-python
Requires-Dist: pillow
Requires-Dist: matplotlib
Requires-Dist: tqdm
